ezcv/__init__.py
ezcv/__main__.py
ezcv/autoreload.py
ezcv/cli.py
ezcv/content.py
ezcv/core.py
ezcv/filters.py
ezcv/themes.py
ezcv/__pycache__/__init__.cpython-312.pyc
ezcv/example_site/.gitignore
ezcv/example_site/flask-README.md
ezcv/example_site/requirements.txt
ezcv/example_site/routes.py
ezcv/example_site/standard-README.md
ezcv/example_site/.github/workflows/ezcv-publish.yml
ezcv/example_site/content/blog/example 2.md
ezcv/example_site/content/blog/example.md
ezcv/example_site/content/education/example-current.md
ezcv/example_site/content/education/example-old.md
ezcv/example_site/content/gallery/P1112419.jpg
ezcv/example_site/content/gallery/P1112490.jpg
ezcv/example_site/content/gallery/P1112566.jpg
ezcv/example_site/content/projects/example.md
ezcv/example_site/content/volunteering_experience/example-current.md
ezcv/example_site/content/volunteering_experience/example-old.md
ezcv/example_site/content/work_experience/example-current.md
ezcv/example_site/content/work_experience/example-old.md
ezcv/example_site/images/abstract-landscape.jpg
ezcv/example_site/images/ice-caps.jpg
ezcv/themes/remotes.yml
ezcv/themes/base/index.jinja
ezcv/themes/base/metadata.yml
ezcv/themes/base/resume.jinja
ezcv/themes/base/sections/education.jinja
ezcv/themes/base/sections/gallery.jinja
ezcv/themes/base/sections/projects.jinja
ezcv/themes/base/sections/volunteering_experience.jinja
ezcv/themes/base/sections/work_experience.jinja
ezcv/themes/base/sections/blog/feed.jinja
ezcv/themes/base/sections/blog/overview.jinja
ezcv/themes/base/sections/blog/single.jinja
ezcv/themes/dimension/LICENSE.txt
ezcv/themes/dimension/README.txt
ezcv/themes/dimension/index.jinja
ezcv/themes/dimension/metadata.yml
ezcv/themes/dimension/resume.jinja
ezcv/themes/dimension/css/fontawesome-all.min.css
ezcv/themes/dimension/css/main.css
ezcv/themes/dimension/css/noscript.css
ezcv/themes/dimension/css/overview-blog.css
ezcv/themes/dimension/css/single-blog.css
ezcv/themes/dimension/images/bg.jpg
ezcv-0.3.5.dist-info/LICENSE
ezcv-0.3.5.dist-info/METADATA
ezcv-0.3.5.dist-info/WHEEL
ezcv-0.3.5.dist-info/entry_points.txt
ezcv-0.3.5.dist-info/top_level.txt
ezcv-0.3.5.dist-info/RECORD
