Metadata-Version: 2.1
Name: ezcv
Version: 0.3.5
Summary: An easy to use personal site generator
Author: Kieran Wood
Author-email: kieran@canadiancoding.ca
Project-URL: User Docs, https://ezcv.readthedocs.io
Project-URL: API Docs, https://kieranwood.ca/ezcv
Project-URL: Forum, https://github.com/Descent098/ezcv/discussions
Project-URL: Source, https://github.com/Descent098/ezcv
Project-URL: Bug Report, https://github.com/Descent098/ezcv/issues/new?assignees=Descent098&labels=bug&template=bug_report.md&title=%5BBUG%5D
Project-URL: Feature Request, https://github.com/Descent098/ezcv/issues/new?labels=enhancement&template=feature_request.md&title=%5BFeature%5D
Project-URL: Roadmap, https://github.com/Descent098/ezcv/projects
Classifier: Programming Language :: Python :: 3
Classifier: Operating System :: OS Independent
Classifier: Development Status :: 4 - Beta
License-File: LICENSE
Requires-Dist: docopt
Requires-Dist: pyyaml
Requires-Dist: jinja2
Requires-Dist: markdown
Requires-Dist: tqdm
Requires-Dist: requests
Requires-Dist: exifread
Requires-Dist: python-markdown-math
Requires-Dist: colored
Requires-Dist: pillow
Requires-Dist: css-html-js-minify
Requires-Dist: livereload
Requires-Dist: flask
Requires-Dist: tornado <6.3.0
Provides-Extra: dev
Requires-Dist: mkdocs ; extra == 'dev'
Requires-Dist: pdoc3 ; extra == 'dev'
